[
  {
    "code": "BJS",
    "countryName": "中国",
    "jp": "bj",
    "initial": "B",
    "py": "beijing",
    "name": "北京",
    "ename": "beijing",
    "portCode": "PEK",
    "portName": "首都国际机场",
    "hotFlag": 2,
    "arriveIndex": 1168026,
    "departIndex": 1166441
  },
  {
    "code": "SHA",
    "countryName": "中国",
    "jp": "sh",
    "initial": "S",
    "py": "shanghai",
    "name": "上海",
    "ename": "shanghai",
    "portCode": "SHA",
    "portName": "虹桥国际机场",
    "hotFlag": 4,
    "arriveIndex": 1165068,
    "departIndex": 1174023
  },
  {
    "code": "CAN",
    "countryName": "中国",
    "jp": "gz",
    "initial": "G",
    "py": "guangzhou",
    "name": "广州",
    "ename": "guangzhou",
    "portCode": "CAN",
    "portName": "新白云国际机场",
    "hotFlag": 5,
    "arriveIndex": 636588,
    "departIndex": 645282
  },
  {
    "code": "SZX",
    "countryName": "中国",
    "jp": "sz",
    "initial": "S",
    "py": "shenzhen",
    "name": "深圳",
    "ename": "shenzhen",
    "portCode": "SZX",
    "portName": "宝安国际机场",
    "hotFlag": 6,
    "arriveIndex": 548092,
    "departIndex": 553384
  },
  {
    "code": "HKG",
    "countryName": "中国",
    "jp": "xg",
    "initial": "X",
    "py": "xianggang",
    "name": "香港",
    "ename": "hongkong",
    "einitial": "H",
    "portCode": "HKG",
    "portName": "香港国际机场",
    "hotFlag": 6,
    "arriveIndex": 0,
    "departIndex": 0
  },
  {
    "code": "CTU",
    "countryName": "中国",
    "jp": "cd",
    "initial": "C",
    "py": "chengdu",
    "name": "成都",
    "ename": "chengdu",
    "portCode": "CTU",
    "portName": "双流国际机场",
    "hotFlag": 7,
    "arriveIndex": 461508,
    "departIndex": 447917
  },
  {
    "code": "HGH",
    "countryName": "中国",
    "jp": "hz",
    "initial": "H",
    "py": "hangzhou",
    "name": "杭州",
    "ename": "hangzhou",
    "portCode": "HGH",
    "portName": "萧山国际机场",
    "hotFlag": 8,
    "arriveIndex": 333384,
    "departIndex": 333136
  },
  {
    "code": "WUH",
    "countryName": "中国",
    "jp": "wh",
    "initial": "W",
    "py": "wuhan",
    "name": "武汉",
    "ename": "wuhan",
    "portCode": "WUH",
    "portName": "天河国际机场",
    "hotFlag": 9,
    "arriveIndex": 218362,
    "departIndex": 217428
  },
  {
    "code": "SIA",
    "countryName": "中国",
    "jp": "xa",
    "initial": "X",
    "py": "xian",
    "name": "西安",
    "ename": "xian",
    "portCode": "XIY",
    "portName": "咸阳国际机场",
    "hotFlag": 10,
    "arriveIndex": 337207,
    "departIndex": 339293
  },
  {
    "code": "CKG",
    "countryName": "中国",
    "jp": "cq",
    "initial": "C",
    "py": "chongqing",
    "name": "重庆",
    "ename": "chongqing",
    "portCode": "CKG",
    "portName": "江北国际机场",
    "hotFlag": 11,
    "arriveIndex": 337698,
    "departIndex": 323711
  },
  {
    "code": "TAO",
    "countryName": "中国",
    "jp": "qd",
    "initial": "Q",
    "py": "qingdao",
    "name": "青岛",
    "ename": "qingdao",
    "portCode": "TAO",
    "portName": "流亭国际机场",
    "hotFlag": 12,
    "arriveIndex": 206145,
    "departIndex": 211628
  },
  {
    "code": "CSX",
    "countryName": "中国",
    "jp": "cs",
    "initial": "C",
    "py": "changsha",
    "name": "长沙",
    "ename": "changsha",
    "portCode": "CSX",
    "portName": "黄花国际机场",
    "hotFlag": 13,
    "arriveIndex": 220199,
    "departIndex": 216745
  },
  {
    "code": "NKG",
    "countryName": "中国",
    "jp": "nj",
    "initial": "N",
    "py": "nanjing",
    "name": "南京",
    "ename": "nanjing",
    "portCode": "NKG",
    "portName": "南京禄口国际机场",
    "hotFlag": 14,
    "arriveIndex": 200015,
    "departIndex": 200129
  },
  {
    "code": "XMN",
    "countryName": "中国",
    "jp": "xm",
    "initial": "X",
    "py": "xiamen",
    "name": "厦门",
    "ename": "xiamen",
    "portCode": "XMN",
    "portName": "高崎国际机场",
    "hotFlag": 15,
    "arriveIndex": 234371,
    "departIndex": 233573
  },
  {
    "code": "KMG",
    "countryName": "中国",
    "jp": "km",
    "initial": "K",
    "py": "kunming",
    "name": "昆明",
    "ename": "kunming",
    "portCode": "KMG",
    "portName": "长水国际机场",
    "hotFlag": 16,
    "arriveIndex": 259674,
    "departIndex": 252499
  },
  {
    "code": "DLC",
    "countryName": "中国",
    "jp": "dl",
    "initial": "D",
    "py": "dalian",
    "name": "大连",
    "ename": "dalian",
    "portCode": "DLC",
    "portName": "周水子国际机场",
    "hotFlag": 17,
    "arriveIndex": 168567,
    "departIndex": 173238
  },
  {
    "code": "TSN",
    "countryName": "中国",
    "jp": "tj",
    "initial": "T",
    "py": "tianjin",
    "name": "天津",
    "ename": "tianjin",
    "portCode": "TSN",
    "portName": "滨海国际机场",
    "hotFlag": 18,
    "arriveIndex": 145648,
    "departIndex": 149170
  },
  {
    "code": "CGO",
    "countryName": "中国",
    "jp": "zz",
    "initial": "Z",
    "py": "zhengzhou",
    "name": "郑州",
    "ename": "zhengzhou",
    "portCode": "CGO",
    "portName": "新郑国际机场",
    "hotFlag": 19,
    "arriveIndex": 174700,
    "departIndex": 176530
  },
  {
    "code": "SYX",
    "countryName": "中国",
    "jp": "sy",
    "initial": "S",
    "py": "sanya",
    "name": "三亚",
    "ename": "sanya",
    "portCode": "SYX",
    "portName": "凤凰国际机场",
    "hotFlag": 20,
    "arriveIndex": 154247,
    "departIndex": 150551
  },
  {
    "code": "TNA",
    "countryName": "中国",
    "jp": "jn",
    "initial": "J",
    "py": "jinan",
    "name": "济南",
    "ename": "jinan",
    "portCode": "TNA",
    "portName": "遥墙国际机场",
    "hotFlag": 21,
    "arriveIndex": 97422,
    "departIndex": 98921
  },
  {
    "code": "FOC",
    "countryName": "中国",
    "jp": "fz",
    "initial": "F",
    "py": "fuzhou",
    "name": "福州",
    "ename": "fuzhou",
    "portCode": "FOC",
    "portName": "长乐国际机场",
    "hotFlag": 22,
    "arriveIndex": 120545,
    "departIndex": 116091
  }
]